jieting_try_tools/__init__.py
jieting_try_tools/tools/__init__.py
jieting_try_tools/tools/jieting_try_tool_1.py
jieting_try_tools/tools/jieting_try_tool_2.py
jieting_try_tools/tools/utils.py
jieting_try_tools/yamls/jieting_try_tool_1.yaml
jieting_try_tools/yamls/jieting_try_tool_2.yaml
tests/__init__.py
tests/test_jieting_try_tool_1.py
jieting_try_tools-0.0.2.dist-info/METADATA
jieting_try_tools-0.0.2.dist-info/WHEEL
jieting_try_tools-0.0.2.dist-info/entry_points.txt
jieting_try_tools-0.0.2.dist-info/top_level.txt
jieting_try_tools-0.0.2.dist-info/RECORD
